{
    "name": "Matthias Strubel",
    "title": "System Engineer z/OS & Linux",
    "email": "m.strubel@bisquitbox.de",
    "phone": "",
    "website": "http://bisquitbox.de/01-matthias/",
    "city": ["Wiesbaden", "Frankfurt", "Mainz" ],
    "keywords": ["z/OS", "Linux", "Netzwerk", "Mainframe"],
    "profiles": {
        "gravatar": "m.strubel@bisquitbox.de",
        "xing": "https://www.xing.com/profile/Matthias_Strubel",
        "twitter": "https://twitter.com/MatthiasStrubel",
        "google+": "",
        "facebook": "",
        "linkedin": "https://www.linkedin.com/in/matthias-strubel-b675b0141/",
        "github": "https://github.com/MaStr",
        "stackoverflow": "",
        "aboutme": "",
        "tumblr": "",
        "500px": "",
        "behance": "",
        "flickr": "",
        "slideshare": "",
        "pinboard": ""
    }
}
