{
  "name": "Steffen Schmidt",
  "title": "Technical Consultant, Projektleiter",
  "email": "mail@steffen-schmidt.com",
  "phone": "+49 151 12 13 88 05",
  "website": "http://www.steffen-schmidt.com",
  "city": [
    "Eltville",
    "Wiesbaden",
    "Mainz",
    "Frankfurt",
    "Darmstadt",
    "Bad Kreuznach",
    "Rüdesheim"
  ],
  "keywords": [
    "ruby on rails",
    "ruby",
    "javascript",
    "jquery",
    "json",
    "xml",
    "html",
    "html5",
    "css",
    "sql",
    "git",
    "oauth2",
    "rest",
    "webentwicklung",
    "webdesign",
    "usability",
    "scrum",
    "agile",
    "kanban",
    "clean code",
    "qualitätssicherung",
    "qa",
    "projektleitung",
    "business development",
    "product owner",
    "produktentwicklung",
    "productdevelopment",
    "entrepreneur",
    "lean startup",
    "co-founding",
    "beratung",
    "workshop moderation",
    "projektmanagement",
    "konzept",
    "design",
    "interim manager",
    "generalist"
  ],
  "profiles": {
    "gravatar": "mail@steffen-schmidt.com",
    "xing": "http://xing.to/steffenschmidt",
    "twitter": "https://twitter.com/steffenschmidt",
    "google+": "",
    "facebook": "",
    "linkedin": "http://www.linkedin.com/in/schmidtsteffen",
    "github": "",
    "stackoverflow": "",
    "aboutme": "",
    "tumblr": "",
    "500px": "",
    "behance": "",
    "flickr": "",
    "slideshare": "",
    "pinboard": ""
  }
}
